yaclogger/__init__.py
yaclogger/yaclogger.py
yaclogger-1.0.0.dist-info/LICENSE
yaclogger-1.0.0.dist-info/METADATA
yaclogger-1.0.0.dist-info/WHEEL
yaclogger-1.0.0.dist-info/top_level.txt
yaclogger-1.0.0.dist-info/RECORD
