Metadata-Version: 2.1
Name: yaclogger
Version: 1.0.0
Summary: Yet Another Colorful Logger is just another logging utility that adds color to your console log messages.
Home-page: https://github.com/wagner-cotta/yaclogger
Author: Wagner Cotta
Author-email: Wagner Cotta <waacotta@gmail.com>
License: GNU GENERAL PUBLIC LICENSE
Project-URL: Homepage, https://github.com/wagnercotta/yaclogger
Project-URL: Issues, https://github.com/wagnercotta/yaclogger/issues
Classifier: Programming Language :: Python :: 3
Classifier: Operating System :: OS Independent
Requires-Python: >=3.7
License-File: LICENSE
Requires-Dist: colorlog ==6.7.0
